{
    "message": "ok",
    "result": {
        "properties": {
            "height": "175",
            "mass": "1,358",
            "hair_color": "n/a",
            "skin_color": "green-tan, brown",
            "eye_color": "orange",
            "birth_year": "600BBY",
            "gender": "hermaphrodite",
            "created": "2022-11-13T10:17:52.686Z",
            "edited": "2022-11-13T10:17:52.686Z",
            "name": "Jabba Desilijic Tiure",
            "homeworld": "https://www.swapi.tech/api/planets/24",
            "url": "https://www.swapi.tech/api/people/16"
        },
        "description": "A person within the Star Wars universe",
        "_id": "5f63a36fee9fd7000499be51",
        "uid": "16",
        "__v": 0
    }
}